ppb_mutant/__init__.py
ppb_mutant/index.py
ppb_mutant/picker.py
ppb_mutant/_assets/__init__.py
ppb_mutant/_assets/agender_100.png
ppb_mutant/_assets/agender_bang.png
ppb_mutant/_assets/agender_furry.png
ppb_mutant/_assets/agender_sweat_drops.png
ppb_mutant/_assets/aliases.txt
ppb_mutant/_assets/androgyne_100.png
ppb_mutant/_assets/androgyne_bang.png
ppb_mutant/_assets/androgyne_furry.png
ppb_mutant/_assets/androgyne_sweat_drops.png
ppb_mutant/_assets/anticipation.png
ppb_mutant/_assets/aromantic_100.png
ppb_mutant/_assets/aromantic_bang.png
ppb_mutant/_assets/aromantic_furry.png
ppb_mutant/_assets/aromantic_sweat_drops.png
ppb_mutant/_assets/asexual_100.png
ppb_mutant/_assets/asexual_bang.png
ppb_mutant/_assets/asexual_furry.png
ppb_mutant/_assets/asexual_sweat_drops.png
ppb_mutant/_assets/avocado_toast.png
ppb_mutant/_assets/bear_100.png
ppb_mutant/_assets/bear_bang.png
ppb_mutant/_assets/bear_furry.png
ppb_mutant/_assets/bear_sweat_drops.png
ppb_mutant/_assets/bigender_100.png
ppb_mutant/_assets/bigender_bang.png
ppb_mutant/_assets/bigender_furry.png
ppb_mutant/_assets/bigender_sweat_drops.png
ppb_mutant/_assets/bisexual_100.png
ppb_mutant/_assets/bisexual_bang.png
ppb_mutant/_assets/bisexual_furry.png
ppb_mutant/_assets/bisexual_sweat_drops.png
ppb_mutant/_assets/bismuth.png
ppb_mutant/_assets/cat_tilting_head.png
ppb_mutant/_assets/civil.png
ppb_mutant/_assets/cursed_eggplant.png
ppb_mutant/_assets/cursed_eyebrows.png
ppb_mutant/_assets/cursed_think.png
ppb_mutant/_assets/demienby_100.png
ppb_mutant/_assets/demienby_bang.png
ppb_mutant/_assets/demienby_furry.png
ppb_mutant/_assets/demienby_sweat_drops.png
ppb_mutant/_assets/demigirl_100.png
ppb_mutant/_assets/demigirl_bang.png
ppb_mutant/_assets/demigirl_furry.png
ppb_mutant/_assets/demigirl_sweat_drops.png
ppb_mutant/_assets/demiguy_100.png
ppb_mutant/_assets/demiguy_bang.png
ppb_mutant/_assets/demiguy_furry.png
ppb_mutant/_assets/demiguy_sweat_drops.png
ppb_mutant/_assets/demisexual_100.png
ppb_mutant-0.11.0.dist-info/METADATA
ppb_mutant-0.11.0.dist-info/WHEEL
ppb_mutant-0.11.0.dist-info/top_level.txt
ppb_mutant-0.11.0.dist-info/RECORD
