Metadata-Version: 2.1
Name: ppb-mutant
Version: 0.11.0
Summary: Mutant Standard for PursuedPyBear
Home-page: https://github.com/ppb/ppb-mutant
Author: Jamie Bliss
Author-email: jamie@ivyleav.es
License: Artistic-2.0
Platform: UNKNOWN
Classifier: Development Status :: 4 - Beta
Classifier: Intended Audience :: Education
Classifier: Intended Audience :: Developers
Classifier: License :: OSI Approved :: Artistic License
Classifier: Natural Language :: English
Classifier: Programming Language :: Python :: 3.7
Classifier: Topic :: Games/Entertainment
Classifier: Topic :: Software Development :: Libraries
Requires-Dist: ppb (~=0.8.0)
